{
  "meta": {
    "baseDate": "2026-04-29",
    "asOfDate": "2026-04-21",
    "windowDays": 7,
    "generatedAt": "2026-04-29T06:08:47.117Z",
    "note": "Informational only. Joint prob is a naive product (independence assumption)."
  },
  "topPicks": [
    {
      "date": "2026-05-02",
      "round": "Matchday 35",
      "home": "Arsenal",
      "away": "Fulham",
      "match": "Arsenal vs Fulham",
      "pick": "H",
      "prob": 0.6743921723104496,
      "xg": [
        2.0208205756276794,
        0.7306911654737741
      ],
      "ml": "2-0"
    },
    {
      "date": "2026-05-01",
      "round": "Matchday 35",
      "home": "Leeds United",
      "away": "Burnley",
      "match": "Leeds United vs Burnley",
      "pick": "H",
      "prob": 0.5814396717523224,
      "xg": [
        2.071027298003522,
        1.1587390793439944
      ],
      "ml": "2-1"
    },
    {
      "date": "2026-05-04",
      "round": "Matchday 35",
      "home": "Everton",
      "away": "Manchester City",
      "match": "Everton vs Manchester City",
      "pick": "A",
      "prob": 0.52321099469251,
      "xg": [
        0.9841658647537399,
        1.6264288003418437
      ],
      "ml": "0-1"
    },
    {
      "date": "2026-05-02",
      "round": "Matchday 35",
      "home": "Brentford",
      "away": "West Ham United",
      "match": "Brentford vs West Ham United",
      "pick": "H",
      "prob": 0.5121456440815895,
      "xg": [
        1.6718838551155706,
        1.0759720022479946
      ],
      "ml": "1-1"
    },
    {
      "date": "2026-05-03",
      "round": "Matchday 35",
      "home": "Manchester United",
      "away": "Liverpool",
      "match": "Manchester United vs Liverpool",
      "pick": "H",
      "prob": 0.44958638836864706,
      "xg": [
        1.740005248884612,
        1.427732079905993
      ],
      "ml": "1-1"
    },
    {
      "date": "2026-05-02",
      "round": "Matchday 35",
      "home": "Newcastle United",
      "away": "Brighton & Hove Albion",
      "match": "Newcastle United vs Brighton & Hove Albion",
      "pick": "A",
      "prob": 0.4162003269151288,
      "xg": [
        1.430891587711524,
        1.600163490522659
      ],
      "ml": "1-1"
    },
    {
      "date": "2026-05-02",
      "round": "Matchday 35",
      "home": "Wolverhampton Wanderers",
      "away": "Sunderland",
      "match": "Wolverhampton Wanderers vs Sunderland",
      "pick": "A",
      "prob": 0.41072762263731183,
      "xg": [
        1.1153879800542386,
        1.31235979062066
      ],
      "ml": "1-1"
    },
    {
      "date": "2026-05-03",
      "round": "Matchday 35",
      "home": "Aston Villa",
      "away": "Tottenham Hotspur",
      "match": "Aston Villa vs Tottenham Hotspur",
      "pick": "H",
      "prob": 0.410667198082761,
      "xg": [
        1.4237599510104106,
        1.2498664672577715
      ],
      "ml": "1-1"
    },
    {
      "date": "2026-05-04",
      "round": "Matchday 35",
      "home": "Chelsea",
      "away": "Nottingham Forest",
      "match": "Chelsea vs Nottingham Forest",
      "pick": "H",
      "prob": 0.38756307280003577,
      "xg": [
        1.3017233837809465,
        1.2082042516825124
      ],
      "ml": "1-1"
    },
    {
      "date": "2026-05-03",
      "round": "Matchday 35",
      "home": "Bournemouth",
      "away": "Crystal Palace",
      "match": "Bournemouth vs Crystal Palace",
      "pick": "A",
      "prob": 0.37561575662729163,
      "xg": [
        1.113825812014947,
        1.184626184626185
      ],
      "ml": "1-1"
    }
  ],
  "combos": {
    "2": {
      "jointProb": 0.3921183633005234,
      "games": [
        {
          "date": "2026-05-02",
          "round": "Matchday 35",
          "home": "Arsenal",
          "away": "Fulham",
          "match": "Arsenal vs Fulham",
          "pick": "H",
          "prob": 0.6743921723104496,
          "xg": [
            2.0208205756276794,
            0.7306911654737741
          ],
          "ml": "2-0"
        },
        {
          "date": "2026-05-01",
          "round": "Matchday 35",
          "home": "Leeds United",
          "away": "Burnley",
          "match": "Leeds United vs Burnley",
          "pick": "H",
          "prob": 0.5814396717523224,
          "xg": [
            2.071027298003522,
            1.1587390793439944
          ],
          "ml": "2-1"
        }
      ]
    },
    "3": {
      "jointProb": 0.20516063889966585,
      "games": [
        {
          "date": "2026-05-02",
          "round": "Matchday 35",
          "home": "Arsenal",
          "away": "Fulham",
          "match": "Arsenal vs Fulham",
          "pick": "H",
          "prob": 0.6743921723104496,
          "xg": [
            2.0208205756276794,
            0.7306911654737741
          ],
          "ml": "2-0"
        },
        {
          "date": "2026-05-01",
          "round": "Matchday 35",
          "home": "Leeds United",
          "away": "Burnley",
          "match": "Leeds United vs Burnley",
          "pick": "H",
          "prob": 0.5814396717523224,
          "xg": [
            2.071027298003522,
            1.1587390793439944
          ],
          "ml": "2-1"
        },
        {
          "date": "2026-05-04",
          "round": "Matchday 35",
          "home": "Everton",
          "away": "Manchester City",
          "match": "Everton vs Manchester City",
          "pick": "A",
          "prob": 0.52321099469251,
          "xg": [
            0.9841658647537399,
            1.6264288003418437
          ],
          "ml": "0-1"
        }
      ]
    },
    "4": {
      "jointProb": 0.10507212754945977,
      "games": [
        {
          "date": "2026-05-02",
          "round": "Matchday 35",
          "home": "Arsenal",
          "away": "Fulham",
          "match": "Arsenal vs Fulham",
          "pick": "H",
          "prob": 0.6743921723104496,
          "xg": [
            2.0208205756276794,
            0.7306911654737741
          ],
          "ml": "2-0"
        },
        {
          "date": "2026-05-01",
          "round": "Matchday 35",
          "home": "Leeds United",
          "away": "Burnley",
          "match": "Leeds United vs Burnley",
          "pick": "H",
          "prob": 0.5814396717523224,
          "xg": [
            2.071027298003522,
            1.1587390793439944
          ],
          "ml": "2-1"
        },
        {
          "date": "2026-05-04",
          "round": "Matchday 35",
          "home": "Everton",
          "away": "Manchester City",
          "match": "Everton vs Manchester City",
          "pick": "A",
          "prob": 0.52321099469251,
          "xg": [
            0.9841658647537399,
            1.6264288003418437
          ],
          "ml": "0-1"
        },
        {
          "date": "2026-05-02",
          "round": "Matchday 35",
          "home": "Brentford",
          "away": "West Ham United",
          "match": "Brentford vs West Ham United",
          "pick": "H",
          "prob": 0.5121456440815895,
          "xg": [
            1.6718838551155706,
            1.0759720022479946
          ],
          "ml": "1-1"
        }
      ]
    },
    "5": {
      "jointProb": 0.04723899834317144,
      "games": [
        {
          "date": "2026-05-02",
          "round": "Matchday 35",
          "home": "Arsenal",
          "away": "Fulham",
          "match": "Arsenal vs Fulham",
          "pick": "H",
          "prob": 0.6743921723104496,
          "xg": [
            2.0208205756276794,
            0.7306911654737741
          ],
          "ml": "2-0"
        },
        {
          "date": "2026-05-01",
          "round": "Matchday 35",
          "home": "Leeds United",
          "away": "Burnley",
          "match": "Leeds United vs Burnley",
          "pick": "H",
          "prob": 0.5814396717523224,
          "xg": [
            2.071027298003522,
            1.1587390793439944
          ],
          "ml": "2-1"
        },
        {
          "date": "2026-05-04",
          "round": "Matchday 35",
          "home": "Everton",
          "away": "Manchester City",
          "match": "Everton vs Manchester City",
          "pick": "A",
          "prob": 0.52321099469251,
          "xg": [
            0.9841658647537399,
            1.6264288003418437
          ],
          "ml": "0-1"
        },
        {
          "date": "2026-05-02",
          "round": "Matchday 35",
          "home": "Brentford",
          "away": "West Ham United",
          "match": "Brentford vs West Ham United",
          "pick": "H",
          "prob": 0.5121456440815895,
          "xg": [
            1.6718838551155706,
            1.0759720022479946
          ],
          "ml": "1-1"
        },
        {
          "date": "2026-05-03",
          "round": "Matchday 35",
          "home": "Manchester United",
          "away": "Liverpool",
          "match": "Manchester United vs Liverpool",
          "pick": "H",
          "prob": 0.44958638836864706,
          "xg": [
            1.740005248884612,
            1.427732079905993
          ],
          "ml": "1-1"
        }
      ]
    },
    "6": {
      "jointProb": 0.01966088655357118,
      "games": [
        {
          "date": "2026-05-02",
          "round": "Matchday 35",
          "home": "Arsenal",
          "away": "Fulham",
          "match": "Arsenal vs Fulham",
          "pick": "H",
          "prob": 0.6743921723104496,
          "xg": [
            2.0208205756276794,
            0.7306911654737741
          ],
          "ml": "2-0"
        },
        {
          "date": "2026-05-01",
          "round": "Matchday 35",
          "home": "Leeds United",
          "away": "Burnley",
          "match": "Leeds United vs Burnley",
          "pick": "H",
          "prob": 0.5814396717523224,
          "xg": [
            2.071027298003522,
            1.1587390793439944
          ],
          "ml": "2-1"
        },
        {
          "date": "2026-05-04",
          "round": "Matchday 35",
          "home": "Everton",
          "away": "Manchester City",
          "match": "Everton vs Manchester City",
          "pick": "A",
          "prob": 0.52321099469251,
          "xg": [
            0.9841658647537399,
            1.6264288003418437
          ],
          "ml": "0-1"
        },
        {
          "date": "2026-05-02",
          "round": "Matchday 35",
          "home": "Brentford",
          "away": "West Ham United",
          "match": "Brentford vs West Ham United",
          "pick": "H",
          "prob": 0.5121456440815895,
          "xg": [
            1.6718838551155706,
            1.0759720022479946
          ],
          "ml": "1-1"
        },
        {
          "date": "2026-05-03",
          "round": "Matchday 35",
          "home": "Manchester United",
          "away": "Liverpool",
          "match": "Manchester United vs Liverpool",
          "pick": "H",
          "prob": 0.44958638836864706,
          "xg": [
            1.740005248884612,
            1.427732079905993
          ],
          "ml": "1-1"
        },
        {
          "date": "2026-05-02",
          "round": "Matchday 35",
          "home": "Newcastle United",
          "away": "Brighton & Hove Albion",
          "match": "Newcastle United vs Brighton & Hove Albion",
          "pick": "A",
          "prob": 0.4162003269151288,
          "xg": [
            1.430891587711524,
            1.600163490522659
          ],
          "ml": "1-1"
        }
      ]
    },
    "7": {
      "jointProb": 0.008075269193090182,
      "games": [
        {
          "date": "2026-05-02",
          "round": "Matchday 35",
          "home": "Arsenal",
          "away": "Fulham",
          "match": "Arsenal vs Fulham",
          "pick": "H",
          "prob": 0.6743921723104496,
          "xg": [
            2.0208205756276794,
            0.7306911654737741
          ],
          "ml": "2-0"
        },
        {
          "date": "2026-05-01",
          "round": "Matchday 35",
          "home": "Leeds United",
          "away": "Burnley",
          "match": "Leeds United vs Burnley",
          "pick": "H",
          "prob": 0.5814396717523224,
          "xg": [
            2.071027298003522,
            1.1587390793439944
          ],
          "ml": "2-1"
        },
        {
          "date": "2026-05-04",
          "round": "Matchday 35",
          "home": "Everton",
          "away": "Manchester City",
          "match": "Everton vs Manchester City",
          "pick": "A",
          "prob": 0.52321099469251,
          "xg": [
            0.9841658647537399,
            1.6264288003418437
          ],
          "ml": "0-1"
        },
        {
          "date": "2026-05-02",
          "round": "Matchday 35",
          "home": "Brentford",
          "away": "West Ham United",
          "match": "Brentford vs West Ham United",
          "pick": "H",
          "prob": 0.5121456440815895,
          "xg": [
            1.6718838551155706,
            1.0759720022479946
          ],
          "ml": "1-1"
        },
        {
          "date": "2026-05-03",
          "round": "Matchday 35",
          "home": "Manchester United",
          "away": "Liverpool",
          "match": "Manchester United vs Liverpool",
          "pick": "H",
          "prob": 0.44958638836864706,
          "xg": [
            1.740005248884612,
            1.427732079905993
          ],
          "ml": "1-1"
        },
        {
          "date": "2026-05-02",
          "round": "Matchday 35",
          "home": "Newcastle United",
          "away": "Brighton & Hove Albion",
          "match": "Newcastle United vs Brighton & Hove Albion",
          "pick": "A",
          "prob": 0.4162003269151288,
          "xg": [
            1.430891587711524,
            1.600163490522659
          ],
          "ml": "1-1"
        },
        {
          "date": "2026-05-02",
          "round": "Matchday 35",
          "home": "Wolverhampton Wanderers",
          "away": "Sunderland",
          "match": "Wolverhampton Wanderers vs Sunderland",
          "pick": "A",
          "prob": 0.41072762263731183,
          "xg": [
            1.1153879800542386,
            1.31235979062066
          ],
          "ml": "1-1"
        }
      ]
    },
    "8": {
      "jointProb": 0.0033162481732903833,
      "games": [
        {
          "date": "2026-05-02",
          "round": "Matchday 35",
          "home": "Arsenal",
          "away": "Fulham",
          "match": "Arsenal vs Fulham",
          "pick": "H",
          "prob": 0.6743921723104496,
          "xg": [
            2.0208205756276794,
            0.7306911654737741
          ],
          "ml": "2-0"
        },
        {
          "date": "2026-05-01",
          "round": "Matchday 35",
          "home": "Leeds United",
          "away": "Burnley",
          "match": "Leeds United vs Burnley",
          "pick": "H",
          "prob": 0.5814396717523224,
          "xg": [
            2.071027298003522,
            1.1587390793439944
          ],
          "ml": "2-1"
        },
        {
          "date": "2026-05-04",
          "round": "Matchday 35",
          "home": "Everton",
          "away": "Manchester City",
          "match": "Everton vs Manchester City",
          "pick": "A",
          "prob": 0.52321099469251,
          "xg": [
            0.9841658647537399,
            1.6264288003418437
          ],
          "ml": "0-1"
        },
        {
          "date": "2026-05-02",
          "round": "Matchday 35",
          "home": "Brentford",
          "away": "West Ham United",
          "match": "Brentford vs West Ham United",
          "pick": "H",
          "prob": 0.5121456440815895,
          "xg": [
            1.6718838551155706,
            1.0759720022479946
          ],
          "ml": "1-1"
        },
        {
          "date": "2026-05-03",
          "round": "Matchday 35",
          "home": "Manchester United",
          "away": "Liverpool",
          "match": "Manchester United vs Liverpool",
          "pick": "H",
          "prob": 0.44958638836864706,
          "xg": [
            1.740005248884612,
            1.427732079905993
          ],
          "ml": "1-1"
        },
        {
          "date": "2026-05-02",
          "round": "Matchday 35",
          "home": "Newcastle United",
          "away": "Brighton & Hove Albion",
          "match": "Newcastle United vs Brighton & Hove Albion",
          "pick": "A",
          "prob": 0.4162003269151288,
          "xg": [
            1.430891587711524,
            1.600163490522659
          ],
          "ml": "1-1"
        },
        {
          "date": "2026-05-02",
          "round": "Matchday 35",
          "home": "Wolverhampton Wanderers",
          "away": "Sunderland",
          "match": "Wolverhampton Wanderers vs Sunderland",
          "pick": "A",
          "prob": 0.41072762263731183,
          "xg": [
            1.1153879800542386,
            1.31235979062066
          ],
          "ml": "1-1"
        },
        {
          "date": "2026-05-03",
          "round": "Matchday 35",
          "home": "Aston Villa",
          "away": "Tottenham Hotspur",
          "match": "Aston Villa vs Tottenham Hotspur",
          "pick": "H",
          "prob": 0.410667198082761,
          "xg": [
            1.4237599510104106,
            1.2498664672577715
          ],
          "ml": "1-1"
        }
      ]
    },
    "9": {
      "jointProb": 0.0012852553322079264,
      "games": [
        {
          "date": "2026-05-02",
          "round": "Matchday 35",
          "home": "Arsenal",
          "away": "Fulham",
          "match": "Arsenal vs Fulham",
          "pick": "H",
          "prob": 0.6743921723104496,
          "xg": [
            2.0208205756276794,
            0.7306911654737741
          ],
          "ml": "2-0"
        },
        {
          "date": "2026-05-01",
          "round": "Matchday 35",
          "home": "Leeds United",
          "away": "Burnley",
          "match": "Leeds United vs Burnley",
          "pick": "H",
          "prob": 0.5814396717523224,
          "xg": [
            2.071027298003522,
            1.1587390793439944
          ],
          "ml": "2-1"
        },
        {
          "date": "2026-05-04",
          "round": "Matchday 35",
          "home": "Everton",
          "away": "Manchester City",
          "match": "Everton vs Manchester City",
          "pick": "A",
          "prob": 0.52321099469251,
          "xg": [
            0.9841658647537399,
            1.6264288003418437
          ],
          "ml": "0-1"
        },
        {
          "date": "2026-05-02",
          "round": "Matchday 35",
          "home": "Brentford",
          "away": "West Ham United",
          "match": "Brentford vs West Ham United",
          "pick": "H",
          "prob": 0.5121456440815895,
          "xg": [
            1.6718838551155706,
            1.0759720022479946
          ],
          "ml": "1-1"
        },
        {
          "date": "2026-05-03",
          "round": "Matchday 35",
          "home": "Manchester United",
          "away": "Liverpool",
          "match": "Manchester United vs Liverpool",
          "pick": "H",
          "prob": 0.44958638836864706,
          "xg": [
            1.740005248884612,
            1.427732079905993
          ],
          "ml": "1-1"
        },
        {
          "date": "2026-05-02",
          "round": "Matchday 35",
          "home": "Newcastle United",
          "away": "Brighton & Hove Albion",
          "match": "Newcastle United vs Brighton & Hove Albion",
          "pick": "A",
          "prob": 0.4162003269151288,
          "xg": [
            1.430891587711524,
            1.600163490522659
          ],
          "ml": "1-1"
        },
        {
          "date": "2026-05-02",
          "round": "Matchday 35",
          "home": "Wolverhampton Wanderers",
          "away": "Sunderland",
          "match": "Wolverhampton Wanderers vs Sunderland",
          "pick": "A",
          "prob": 0.41072762263731183,
          "xg": [
            1.1153879800542386,
            1.31235979062066
          ],
          "ml": "1-1"
        },
        {
          "date": "2026-05-03",
          "round": "Matchday 35",
          "home": "Aston Villa",
          "away": "Tottenham Hotspur",
          "match": "Aston Villa vs Tottenham Hotspur",
          "pick": "H",
          "prob": 0.410667198082761,
          "xg": [
            1.4237599510104106,
            1.2498664672577715
          ],
          "ml": "1-1"
        },
        {
          "date": "2026-05-04",
          "round": "Matchday 35",
          "home": "Chelsea",
          "away": "Nottingham Forest",
          "match": "Chelsea vs Nottingham Forest",
          "pick": "H",
          "prob": 0.38756307280003577,
          "xg": [
            1.3017233837809465,
            1.2082042516825124
          ],
          "ml": "1-1"
        }
      ]
    },
    "10": {
      "jointProb": 0.00048276215406654134,
      "games": [
        {
          "date": "2026-05-02",
          "round": "Matchday 35",
          "home": "Arsenal",
          "away": "Fulham",
          "match": "Arsenal vs Fulham",
          "pick": "H",
          "prob": 0.6743921723104496,
          "xg": [
            2.0208205756276794,
            0.7306911654737741
          ],
          "ml": "2-0"
        },
        {
          "date": "2026-05-01",
          "round": "Matchday 35",
          "home": "Leeds United",
          "away": "Burnley",
          "match": "Leeds United vs Burnley",
          "pick": "H",
          "prob": 0.5814396717523224,
          "xg": [
            2.071027298003522,
            1.1587390793439944
          ],
          "ml": "2-1"
        },
        {
          "date": "2026-05-04",
          "round": "Matchday 35",
          "home": "Everton",
          "away": "Manchester City",
          "match": "Everton vs Manchester City",
          "pick": "A",
          "prob": 0.52321099469251,
          "xg": [
            0.9841658647537399,
            1.6264288003418437
          ],
          "ml": "0-1"
        },
        {
          "date": "2026-05-02",
          "round": "Matchday 35",
          "home": "Brentford",
          "away": "West Ham United",
          "match": "Brentford vs West Ham United",
          "pick": "H",
          "prob": 0.5121456440815895,
          "xg": [
            1.6718838551155706,
            1.0759720022479946
          ],
          "ml": "1-1"
        },
        {
          "date": "2026-05-03",
          "round": "Matchday 35",
          "home": "Manchester United",
          "away": "Liverpool",
          "match": "Manchester United vs Liverpool",
          "pick": "H",
          "prob": 0.44958638836864706,
          "xg": [
            1.740005248884612,
            1.427732079905993
          ],
          "ml": "1-1"
        },
        {
          "date": "2026-05-02",
          "round": "Matchday 35",
          "home": "Newcastle United",
          "away": "Brighton & Hove Albion",
          "match": "Newcastle United vs Brighton & Hove Albion",
          "pick": "A",
          "prob": 0.4162003269151288,
          "xg": [
            1.430891587711524,
            1.600163490522659
          ],
          "ml": "1-1"
        },
        {
          "date": "2026-05-02",
          "round": "Matchday 35",
          "home": "Wolverhampton Wanderers",
          "away": "Sunderland",
          "match": "Wolverhampton Wanderers vs Sunderland",
          "pick": "A",
          "prob": 0.41072762263731183,
          "xg": [
            1.1153879800542386,
            1.31235979062066
          ],
          "ml": "1-1"
        },
        {
          "date": "2026-05-03",
          "round": "Matchday 35",
          "home": "Aston Villa",
          "away": "Tottenham Hotspur",
          "match": "Aston Villa vs Tottenham Hotspur",
          "pick": "H",
          "prob": 0.410667198082761,
          "xg": [
            1.4237599510104106,
            1.2498664672577715
          ],
          "ml": "1-1"
        },
        {
          "date": "2026-05-04",
          "round": "Matchday 35",
          "home": "Chelsea",
          "away": "Nottingham Forest",
          "match": "Chelsea vs Nottingham Forest",
          "pick": "H",
          "prob": 0.38756307280003577,
          "xg": [
            1.3017233837809465,
            1.2082042516825124
          ],
          "ml": "1-1"
        },
        {
          "date": "2026-05-03",
          "round": "Matchday 35",
          "home": "Bournemouth",
          "away": "Crystal Palace",
          "match": "Bournemouth vs Crystal Palace",
          "pick": "A",
          "prob": 0.37561575662729163,
          "xg": [
            1.113825812014947,
            1.184626184626185
          ],
          "ml": "1-1"
        }
      ]
    }
  }
}